[{"hname":"Dhaka medical","husername":"dhaka medical","hpassword":"#12345678","hemail":"dhakamedical@gmail.com","hlocation":"Dhaka medical and hospital, Dhaka","hphone":"01680221295","hedate":"1997-01-08","hosid":"5465412","hicuseatno":"35","hoswno":"85","hosnoseat":"1500","hcabinno":"75","hoxav":"Yes"},{"hname":"","husername":"","hpassword":"","hemail":"","hlocation":"","hphone":"","hedate":"","hosid":"","hicuseatno":"","hoswno":"","hosnoseat":"","hcabinno":"","hoxav":""},{"hname":"","husername":"","hpassword":"","hemail":"","hlocation":"","hphone":"","hedate":"","hosid":"","hicuseatno":"","hoswno":"","hosnoseat":"","hcabinno":"","hoxav":""},{"hname":"","husername":"","hpassword":"","hemail":"","hlocation":"","hphone":"","hedate":"","hosid":"","hicuseatno":"","hoswno":"","hosnoseat":"","hcabinno":"","hoxav":""},{"hname":"R","husername":"","hpassword":"","hemail":"","hlocation":"","hphone":"","hedate":"","hosid":"","hicuseatno":"","hoswno":"","hosnoseat":"","hcabinno":"","hoxav":"none"},{"hname":"Rangpur medical","husername":"rangpur medical","hpassword":"$123456789","hemail":"rangpurmedical@gmail.com","hlocation":"Rangpur medical and hospital","hphone":"01789564546","hedate":"2009-02-03","hosid":"45654","hicuseatno":"45","hoswno":"20","hosnoseat":"1500","hcabinno":"55","hoxav":"Yes"},{"hname":"Rangpur medical","husername":"rangpur medical","hpassword":"$123456789","hemail":"rangpurmedical@gmail.com","hlocation":"Rangpur medical and hospital","hphone":"01789564546","hedate":"2009-02-03","hosid":"45654","hicuseatno":"45","hoswno":"20","hosnoseat":"1500","hcabinno":"55","hoxav":"Yes"}]